{
  "coin": {
    "name": "Crown",
    "shortcut": "CRW",
    "label": "Crown",
    "alias": "crown"
  },
  "ports": {
    "backend_rpc": 8030,
    "backend_message_queue": 38330,
    "blockbook_internal": 9030,
    "blockbook_public": 9130
  },
  "ipc": {
    "rpc_url_template": "http://127.0.0.1:{{.Ports.BackendRPC}}",
    "rpc_user": "rpc",
    "rpc_pass": "rpc",
    "rpc_timeout": 25,
    "message_queue_binding_template": "tcp://127.0.0.1:{{.Ports.BackendMessageQueue}}"
  },
  "backend": {
    "package_name": "backend-crown",
    "package_revision": "polispay",
    "system_user": "crown",
    "version": "0.14.0.1",
    "binary_url": "https://github.com/Crowndev/crown-core/releases/download/v0.14.0.1-Emerald/Crown-0.14.0.1-Linux64.zip",
    "verification_type": "sha256",
    "verification_source": "07ef11bb51bd6b57b549abffa9af3b3138a260cb29b9eaa253bead3545dfdf32",
    "extract_command": "unzip -j -d backend",
    "exclude_files": [
      "bin/test_crown-qt",
      "bin/text_crown",
      "bin/crown-tx",
      "bin/crown-qt"
    ],
    "exec_command_template": "{{.Env.BackendInstallPath}}/{{.Coin.Alias}}/bin/crownd -datadir={{.Env.BackendDataPath}}/{{.Coin.Alias}}/backend -conf={{.Env.BackendInstallPath}}/{{.Coin.Alias}}/{{.Coin.Alias}}.conf -pid=/run/{{.Coin.Alias}}/{{.Coin.Alias}}.pid",
    "logrotate_files_template": "{{.Env.BackendDataPath}}/{{.Coin.Alias}}/backend/*.log",
    "postinst_script_template": "",
    "service_type": "forking",
    "service_additional_params_template": "",
    "protect_memory": true,
    "mainnet": true,
    "server_config_file": "bitcoin_like.conf",
    "client_config_file": "bitcoin_like_client.conf",
    "additional_params": {
      "deprecatedrpc": "estimatefee"
    }
  },
  "blockbook": {
    "package_name": "blockbook-crown",
    "system_user": "blockbook-crown",
    "internal_binding_template": ":{{.Ports.BlockbookInternal}}",
    "public_binding_template": ":{{.Ports.BlockbookPublic}}",
    "explorer_url": "",
    "additional_params": "",
    "block_chain": {
      "parse": true,
      "mempool_workers": 8,
      "mempool_sub_workers": 2,
      "block_addresses_to_keep": 300,
      "xpub_magic": 76067358,
      "slip44": 72,
      "additional_params": {}
    }
  },
  "meta": {
    "package_maintainer": "",
    "package_maintainer_email": ""
  }
}